{
  "timestamp": "2026-01-17T20:28:47.022Z",
  "verdict": "WARNING",
  "summary": {
    "total": 4,
    "passed": 3,
    "failed": 1,
    "criticalFailed": 0
  },
  "results": [
    {
      "name": "TypeScript Compilation",
      "passed": true,
      "critical": true,
      "duration": 9099
    },
    {
      "name": "Production Build",
      "passed": true,
      "critical": true,
      "duration": 19767
    },
    {
      "name": "Rules Engine Unit Tests",
      "passed": true,
      "critical": true,
      "duration": 1255
    },
    {
      "name": "Database Parity Check",
      "passed": false,
      "critical": false,
      "error": "Command failed: npx tsx scripts/verify-db-parity.ts",
      "duration": 1674
    }
  ]
}